getsubtitle/__init__.py
getsubtitle/archive.py
getsubtitle/constants.py
getsubtitle/main.py
getsubtitle/progress_bar.py
getsubtitle/subhd.py
getsubtitle/sys_global_var.py
getsubtitle/utils.py
getsubtitle/zimuku.py
getsubtitle/zimuzu.py
getsubtitle-2019.12.5.dist-info/entry_points.txt
getsubtitle-2019.12.5.dist-info/LICENSE
getsubtitle-2019.12.5.dist-info/WHEEL
getsubtitle-2019.12.5.dist-info/METADATA
getsubtitle-2019.12.5.dist-info/RECORD
